kernel_cms.py
kernel_cms-0.1.dist-info/METADATA
kernel_cms-0.1.dist-info/WHEEL
kernel_cms-0.1.dist-info/top_level.txt
kernel_cms-0.1.dist-info/RECORD
